hurdur/__init__.py
hurdur-0.1.0.dist-info/METADATA
hurdur-0.1.0.dist-info/WHEEL
hurdur-0.1.0.dist-info/licenses/LICENSE
hurdur-0.1.0.dist-info/RECORD
