Metadata-Version: 2.1
Name: hurdur
Version: 0.1.0
Summary: Small library for human-readable durations in Python
Project-URL: Repository, https://github.com/axesilo/hurdur.git
Author-email: David Carroll <d.matthew.carroll@gmail.com>
License: MIT License
License-File: LICENSE
